Workbook

Sheet Banks
A1: id | B1: name
A2: 1 | B2: HDFC
A3: 2 | B3: UNION
A4: 3 | B4: INDUSIND
A5: 4 | B5: SBI
A6: 5 | B6: AXIS

Sheet Users
A1: id | B1: full_name | C1: username | D1: email | E1: password_hash | F1: zerodha_api_key | G1: zerodha_api_secret | H1: zerodha_access_token | I1: zerodha_public_token | J1: zerodha_user_id | K1: zerodha_user_name | L1: zerodha_token_expires_at | M1: zerodha_connected_at | N1: zerodha_last_sync_at | O1: created_at
A2: 1 | B2: Venkat Teja Vasa | C2: venkattj | D2: venkattejavasa08@gmail.com | E2: scrypt:32768:8:1$DvVeiyIIEefkSHDM$0f23094b1120cd24a9102fc860661958845e4671780200d96c7e29661633c359ebb879244ce4ebc647a6081229a2dea5d86ff6d0c19e382e73952444a78614e9 | F2: k3l7bilkzsief2js | G2: 8yj2kuv5rtkdj73ehr008jbsj9rjkt0f | H2: aSvA3ay3VN2Ygm5L4t69j7Muc7Bvwwjs | I2: Q9Ia1GdUnKOT26LWyJcmCVECV3rrcJqH | J2: BOB548 | K2: Vasa Venkat Teja | L2: 2026-03-31 | M2: 2026-03-31 | N2: 2026-03-31 | O2: 2026-03-31
A3: 2 | B3: Rukmini Vasa | O3: 2026-03-31

Sheet bank_accounts
A1: id | B1: user_id | C1: bank_id | D1: balance | E1: purpose
A2: 1 | B2: 1 | C2: 1 | D2: 180211.65 | E2: SALARY
A3: 2 | B3: 1 | C3: 2 | D3: 3785.6 | E3: MUTAL FUNDS
A4: 3 | B4: 1 | C4: 3 | D4: 1660.64 | E4: Transactions
A5: 4 | B5: 2 | C5: 4 | D5: 80672.44 | E5: SALARY
A6: 5 | B6: 2 | C6: 2 | D6: 2908.01 | E6: Pension
A7: 6 | B7: 2 | C7: 3 | D7: 9652.18 | E7: Transactions

Sheet Fixed Deposit
A1: S.No | B1: account_id | C1: Invested | D1: Interest Rate | E1: Maturity Date | F1: Created Date | G1: TODAY | H1: Current Amount | I1: Days To Mature
A2: 1 | B2: 1 | C2: 100000 | D2: 7.25 | E2: 2026-04-09 | F2: 2024-08-08 | G2: =TODAY() -> 46119 | H2: 111997.26 | I2: =E2-G2 -> 2
A3: 2 | B3: 6 | C3: 100000 | D3: 7.99 | E3: 2026-05-16 | F3: 2024-12-16 | G3: =TODAY() -> 46119 | H3: 110376.05 | I3: =E3-G3 -> 39
A4: 3 | B4: 6 | C4: 100000 | D4: 7.99 | E4: 2026-05-17 | F4: 2024-12-17 | G4: =TODAY() -> 46119 | H4: 110354.16 | I4: =E4-G4 -> 40
A5: 4 | B5: 3 | C5: 78248 | D5: 7.75 | E5: 2026-06-04 | F5: 2025-06-04 | G5: =TODAY() -> 46119 | H5: 83298.748 | I5: =E5-G5 -> 58
A6: 5 | B6: 1 | C6: 100000 | D6: 7.25 | E6: 2026-06-20 | F6: 2024-12-20 | G6: =TODAY() -> 46119 | H6: 109335.62 | I6: =E6-G6 -> 74
A7: 6 | B7: 3 | C7: 100000 | D7: 7 | E7: 2026-07-20 | F7: 2025-06-21 | G7: =TODAY() -> 46119 | H7: 105504.11 | I7: =E7-G7 -> 104
A8: 7 | B8: 3 | C8: 100000 | D8: 7 | E8: 2026-08-05 | F8: 2025-07-05 | G8: =TODAY() -> 46119 | H8: 105235.62 | I8: =E8-G8 -> 120
A9: 8 | B9: 3 | C9: 100000 | D9: 7 | E9: 2026-08-05 | F9: 2025-06-21 | G9: =TODAY() -> 46119 | H9: 105504.11 | I9: =E9-G9 -> 120
A10: 9 | B10: 3 | C10: 100000 | D10: 7 | E10: 2026-08-21 | F10: 2025-06-21 | G10: =TODAY() -> 46119 | H10: 105504.11 | I10: =E10-G10 -> 136
A11: 10 | B11: 1 | C11: 100000 | D11: 6.85 | E11: 2026-09-02 | F11: 2025-06-02 | G11: =TODAY() -> 46119 | H11: 105742.74 | I11: =E11-G11 -> 148
A12: 11 | B12: 6 | C12: 100000 | D12: 7 | E12: 2026-09-12 | F12: 2024-08-12 | G12: =TODAY() -> 46119 | H12: 111506.85 | I12: =E12-G12 -> 158
A13: 12 | B13: 6 | C13: 100000 | D13: 7 | E13: 2026-09-18 | F13: 2025-08-18 | G13: =TODAY() -> 46119 | H13: 104391.78 | I13: =E13-G13 -> 164
... A39: 38 | B39: 1 | C39: 55992.2 | D39: 6.45 | E39: 2027-09-30 | F39: 2026-01-01 | G39: =TODAY() -> 46119 | H39: 56912.39 | I39: =E39-G39 -> 541
C42: =SUM(Table4[Invested]) -> 4734240.2 | H42: =SUM(Table4[Current Amount]) -> 4901776.3

Sheet Stocks
A1: S.No | B1: Symbol | C1: Exchange | D1: ISIN | E1: Average Price | F1: Current Price | G1: Quantity | H1: Source | I1: Invested | J1: current
A2: 1 | B2: JPM | C2: ASE | D2: US46625H1005 | E2: 24465.104 | F2: 27489.132 | G2: 13.4886 | H2: jpmc | I2: =Table5[[#This Row],[Average Price]]*Table5[[#This Row],[Quantity]] -> 330000 | J2: =Table5[[#This Row],[Current Price]]*Table5[[#This Row],[Quantity]] -> 370789.91
A3: 2 | B3: PIRAMALFIN | C3: BSE | D3: INE202B01038 | E3: 999.33333 | F3: 1721.5 | G3: 9 | H3: zerodha | I3: =Table5[[#This Row],[Average Price]]*Table5[[#This Row],[Quantity]] -> 8994 | J3: =Table5[[#This Row],[Current Price]]*Table5[[#This Row],[Quantity]] -> 15493.5
A4: 3 | B4: SBIN | C4: BSE | D4: INE062A01020 | E4: 783.17308 | F4: 1032.65 | G4: 13 | H4: zerodha | I4: =Table5[[#This Row],[Average Price]]*Table5[[#This Row],[Quantity]] -> 10181.25 | J4: =Table5[[#This Row],[Current Price]]*Table5[[#This Row],[Quantity]] -> 13424.45
A5: 4 | B5: BEL | C5: NSE | D5: INE263A01024 | E5: 350.31061 | F5: 427.15 | G5: 33 | H5: zerodha | I5: =Table5[[#This Row],[Average Price]]*Table5[[#This Row],[Quantity]] -> 11560.25 | J5: =Table5[[#This Row],[Current Price]]*Table5[[#This Row],[Quantity]] -> 14095.95
A6: 5 | B6: LLOYDSME | C6: BSE | D6: INE281B01032 | E6: 1200.7875 | F6: 1431.9 | G6: 12 | H6: zerodha | I6: =Table5[[#This Row],[Average Price]]*Table5[[#This Row],[Quantity]] -> 14409.45 | J6: =Table5[[#This Row],[Current Price]]*Table5[[#This Row],[Quantity]] -> 17182.8
A7: 6 | B7: PRICOLLTD | C7: NSE | D7: INE726V01018 | E7: 460.6619 | F7: 534.3 | G7: 20 | H7: zerodha | I7: =Table5[[#This Row],[Average Price]]*Table5[[#This Row],[Quantity]] -> 9213.2381 | J7: =Table5[[#This Row],[Current Price]]*Table5[[#This Row],[Quantity]] -> 10686
A8: 7 | B8: BHEL | C8: NSE | D8: INE257A01026 | E8: 234.55246 | F8: 245.64 | G8: 57 | H8: zerodha | I8: =Table5[[#This Row],[Average Price]]*Table5[[#This Row],[Quantity]] -> 13369.49 | J8: =Table5[[#This Row],[Current Price]]*Table5[[#This Row],[Quantity]] -> 14001.48
A9: 8 | B9: CGPOWER | C9: NSE | D9: INE067A01029 | E9: 647.45714 | F9: 687.3 | G9: 21 | H9: zerodha | I9: =Table5[[#This Row],[Average Price]]*Table5[[#This Row],[Quantity]] -> 13596.6 | J9: =Table5[[#This Row],[Current Price]]*Table5[[#This Row],[Quantity]] -> 14433.3
A10: 9 | B10: PAYTM | C10: NSE | D10: INE982J01020 | E10: 958.55 | F10: 1029.1 | G10: 14 | H10: zerodha | I10: =Table5[[#This Row],[Average Price]]*Table5[[#This Row],[Quantity]] -> 13419.7 | J10: =Table5[[#This Row],[Current Price]]*Table5[[#This Row],[Quantity]] -> 14407.4
A11: 10 | B11: POWERGRID | C11: NSE | D11: INE752E01010 | E11: 286.868 | F11: 295.15 | G11: 50 | H11: zerodha | I11: =Table5[[#This Row],[Average Price]]*Table5[[#This Row],[Quantity]] -> 14343.4 | J11: =Table5[[#This Row],[Current Price]]*Table5[[#This Row],[Quantity]] -> 14757.5
A12: 11 | B12: AADHARHFC | C12: BSE | D12: INE883F01010 | E12: 439.73939 | F12: 450.3 | G12: 33 | H12: zerodha | I12: =Table5[[#This Row],[Average Price]]*Table5[[#This Row],[Quantity]] -> 14511.4 | J12: =Table5[[#This Row],[Current Price]]*Table5[[#This Row],[Quantity]] -> 14859.9
A13: 12 | B13: SAGILITY | C13: BSE | D13: INE0W2G01015 | E13: 42.148456 | F13: 42.43 | G13: 311 | H13: zerodha | I13: =Table5[[#This Row],[Average Price]]*Table5[[#This Row],[Quantity]] -> 13108.17 | J13: =Table5[[#This Row],[Current Price]]*Table5[[#This Row],[Quantity]] -> 13195.73
... A22: 21 | B22: MEDANTA | C22: BSE | D22: INE474Q01031 | E22: 1217.3286 | F22: 1033.1 | G22: 13 | H22: zerodha | I22: =Table5[[#This Row],[Average Price]]*Table5[[#This Row],[Quantity]] -> 15825.271 | J22: =Table5[[#This Row],[Current Price]]*Table5[[#This Row],[Quantity]] -> 13430.3
I25: =SUM(Table5[Invested]) -> 605317.5 | J25: =SUM(Table5[current]) -> 655326.75

Sheet Mutal Funds
A1: S.No | B1: id | C1: fund_name | D1: scheme_code | E1: units | F1: average_nav | G1: nav_synced_at | H1: latest_nav | I1: nav_date | J1: sip | K1: Invested | L1: Current
A2: 1 | B2: 1 | C2: Nippon India Credit Risk Fund Direct Growth | D2: 118780 | E2: 449.133 | F2: 40.0752 | G2: 46119.041 | H2: 40.6639 | J2: 3000 | K2: =Table7[[#This Row],[average_nav]]*Table7[[#This Row],[units]] -> 17999.095 | L2: =Table7[[#This Row],[latest_nav]]*Table7[[#This Row],[units]] -> 18263.499
A3: 2 | B3: 2 | C3: Quant Small Cap Fund Direct Plan Growth | D3: 120828 | E3: 357.864 | F3: 257.0666 | G3: 46119.041 | H3: 247.9952 | J3: 3000 | K3: =Table7[[#This Row],[average_nav]]*Table7[[#This Row],[units]] -> 91994.882 | L3: =Table7[[#This Row],[latest_nav]]*Table7[[#This Row],[units]] -> 88748.554
A4: 3 | B4: 3 | C4: Nippon India Small Cap Fund Direct Growth | D4: 118778 | E4: 487.833 | F4: 174.2305 | G4: 46119.041 | H4: 169.9426 | J4: 3000 | K4: =Table7[[#This Row],[average_nav]]*Table7[[#This Row],[units]] -> 84995.388 | L4: =Table7[[#This Row],[latest_nav]]*Table7[[#This Row],[units]] -> 82903.608
A5: 4 | B5: 4 | C5: HDFC Balanced Advantage Fund Direct Growth | D5: 118968 | E5: 181.345 | F5: 512.8045 | G5: 46119.041 | H5: 531.019 | J5: 3000 | K5: =Table7[[#This Row],[average_nav]]*Table7[[#This Row],[units]] -> 92994.532 | L5: =Table7[[#This Row],[latest_nav]]*Table7[[#This Row],[units]] -> 96297.641
A6: 5 | B6: 5 | C6: HDFC Infrastructure Fund Direct Growth | D6: 118979 | E6: 1765.835 | F6: 49.2971 | G6: 46119.041 | H6: 47.88 | J6: 3000 | K6: =Table7[[#This Row],[average_nav]]*Table7[[#This Row],[units]] -> 87050.545 | L6: =Table7[[#This Row],[latest_nav]]*Table7[[#This Row],[units]] -> 84548.18
A7: 6 | B7: 6 | C7: PGIM India Midcap Fund Direct Growth | D7: 125307 | E7: 1070.742 | F7: 67.2398 | G7: 46119.041 | H7: 66.29 | J7: 3000 | K7: =Table7[[#This Row],[average_nav]]*Table7[[#This Row],[units]] -> 71996.478 | L7: =Table7[[#This Row],[latest_nav]]*Table7[[#This Row],[units]] -> 70979.487
A8: 7 | B8: 7 | C8: ICICI Prudential NASDAQ 100 Index Fund Direct Growth | D8: 149219 | E8: 3471.197 | F8: 15.0487 | G8: 46119.041 | H8: 19.5154 | J8: 3000 | K8: =Table7[[#This Row],[average_nav]]*Table7[[#This Row],[units]] -> 52237.002 | L8: =Table7[[#This Row],[latest_nav]]*Table7[[#This Row],[units]] -> 67741.798
A9: 8 | B9: 8 | C9: Bandhan Nifty 50 Index Fund Direct Plan Growth | D9: 118482 | E9: 1388.692 | F9: 51.1247 | G9: 46119.041 | H9: 50.5191 | J9: 3000 | K9: =Table7[[#This Row],[average_nav]]*Table7[[#This Row],[units]] -> 70996.462 | L9: =Table7[[#This Row],[latest_nav]]*Table7[[#This Row],[units]] -> 70155.47
A10: 9 | B10: 9 | C10: ICICI Prudential Commodities Fund Direct Growth | D10: 147662 | E10: 1729.322 | F10: 41.6328 | G10: 46119.041 | H10: 46.91 | J10: 3000 | K10: =Table7[[#This Row],[average_nav]]*Table7[[#This Row],[units]] -> 71996.517 | L10: =Table7[[#This Row],[latest_nav]]*Table7[[#This Row],[units]] -> 81122.495
A11: 10 | B11: 10 | C11: nps | E11: 1 | F11: 192845.1 | H11: 185704.67 | J11: 10460 | K11: =Table7[[#This Row],[average_nav]]*Table7[[#This Row],[units]] -> 192845.1 | L11: =Table7[[#This Row],[latest_nav]]*Table7[[#This Row],[units]] -> 185704.67
K13: =SUM(Table7[Invested]) -> 835106 | L13: =SUM(Table7[Current]) -> 846465.4

Sheet Utility Bills
A1: SNO | B1: Type | C1: Amount
A2: 1 | B2: Milk | C2: 1300
A3: 2 | B3: Grocery | C3: 5000
A4: 3 | B4: Fuel | C4: 1000
A5: 4 | B5: Medicine | C5: 750
A6: 5 | B6: Food | C6: 2000
A7: 6 | B7: Gas | C7: 855
A8: 7 | B8: Electricity | C8: 1000
A9: 8 | B9: Mainatanace | C9: 750
A10: 9 | B10: Water Bill | C10: 200
A11: 10 | B11: Internet | C11: 1000

Sheet Loans
A1: S.No | B1: Borrower | C1: Amount | D1: Interest Rate
A2: 1 | B2: Srinivas Mama | C2: 1000000 | D2: 15
A3: 2 | B3: Venkatesh Babai | C3: 1040000 | D3: 15
A4: 3 | B4: Ramesh Uncle | C4: 400000 | D4: 15
A5: 4 | B5: sneha | C5: 84085 | D5: 0
A6: 5 | B6: Home Loan | C6: -591716.86 | D6: 8.35
A7: 6 | B7: Gratuity | C7: 258404 | D7: 0
A8: 7 | B8: PF | C8: 898326 | D8: 8.25

Sheet Earnings
A1: S.No | B1: Income Type | C1: S.No | D1: Income Type | E1: Amount | F1: Person | G1: Source
A2: 1 | C2: 1 | D2: Salary | E2: 170501 | F2: Teja | G2: JPMC
A3: 2 | C3: 2 | D3: Intrest | E3: 10000 | F3: Rukmini | G3: Ramesh
A4: 3 | C4: 3 | D4: Intrest | E4: 12500 | F4: Teja | G4: Srinivas | K4: Total | L4: =SUM(E2:E8) -> 347771
A5: 4 | C5: 4 | D5: Intrest | E5: 13000 | F5: Rukmini | G5: Venkatesh
A6: 5 | C6: 5 | D6: Salary | E6: 45000 | F6: Teja | G6: Prasad
A7: 6 | C7: 6 | D7: Pension | E7: 2016 | F7: Rukmini | G7: PM
A8: 7 | C8: 7 | D8: Salary | E8: 94754 | F8: Manideep | G8: AXIS

Sheet Spending
A1: Spending Type | B1: Amount | C1: Person | D1: Recipient
A2: Chit | B2: 40000 | C2: Teja | D2: Srinivas Mama
A3: Chit | B3: 13000 | C3: Rukmini | D3: Venkatesh Babai
A4: SIP | B4: 27000 | C4: Teja | D4: Muatal Funds
A5: EMI | B5: 30446 | C5: Teja | D5: LIC
A6: SIP | B6: 35000 | C6: Teja | D6: Stocks
A7: Chit | B7: 28000 | C7: Teja | D7: Ramesh Uncle

Sheet Standard_Chits
A1: SNO | B1: Organsation | C1: Value | D1: duration | E1: paid | F1: emi | G1: maturity | H1: Started | I1: Current_value
A2: 1 | B2: Srinivas Mama | C2: 1200000 | D2: 25 | E2: =ROUND((J2-H2)*12/365,0)+1 -> 3 | F2: 40000 | G2: 46799 | H2: 46039 | I2: =E2/D2*C2 -> 144000 | J2: =TEXT(TODAY(), "MMM-yy") -> Apr-26
A3: 2 | B3: Venkatesh Babai | C3: 500000 | D3: 32 | E3: =ROUND((J3-H3)*12/365,0)+1 -> 35 | F3: 13000 | G3: 46054 | H3: 45078 | I3: =E3/D3*C3 -> 546875 | J3: =TEXT(TODAY(), "MMM-yy") -> Apr-26
H4: total | I4: =I2+I3 -> 690875
E5: =(J2-H2)*12/365 -> 2.4328767

Sheet Variable_Chit
A1: Name | B1: Value | C1: Months | D1: maturity | E1: total_paid | F1: start date | G1: net_value | H1: emi_paid
A2: Ramesh | B2: 758000 | C2: 25 | D2: 46296 | E2: =SUM(B6:B30) -> 161240 | F2: 45207 | G2: =B2/C2*H2 -> 181920 | H2: 6
A5: emi no | B5: amount | C5: date
A6: 1 | B6: 29280 | C6: 45968 | F6: 25280 | G6: 45207
A7: 2 | B7: 24960 | C7: 45996 | F7: 25000 | G7: 45238
A8: 3 | B8: 24960 | C8: 46028 | F8: 24960 | G8: 45268
A9: 4 | B9: 31680 | C9: 46057 | F9: 31680 | G9: 45299
A10: 5 | B10: 24960 | C10: 46087 | F10: 24960 | G10: 45330
A11: 6 | B11: 25400 | C11: 46119 | F11: 24860 | G11: 45359
A12: 7 | F12: 25440 | G12: 45390
A13: 8 | F13: 25960 | G13: 45420
A14: 9 | F14: 26560 | G14: 45451
A15: 10 | F15: 27360 | G15: 45481
A16: 11 | F16: 27760 | G16: 45512
A17: 12 | F17: 28360 | G17: 45543
A18: 13 | F18: 28960 | G18: 45573
A19: 14 | F19: 29140 | G19: 45604
A20: 15 | F20: 29760 | G20: 45634
A21: 16 | F21: 29760 | G21: 45665
A22: 17 | F22: 30120 | G22: 45696
A23: 18 | F23: 30560 | G23: 45724
... A30: 25 | F30: 31780 | G30: 45938
F31: =SUM(F6:F30) -> 716420

Sheet sneha
A1: S.No | B1: Payment Date | C1: Amount | D1: Principal Balance
A2: 1 | B2: 2024-09-04 | C2: 4368 | D2: 84085
A3: 2 | B3: 2024-10-04 | C3: 4368
A4: 3 | B4: 2024-11-04 | C4: 4369
A5: 4 | B5: 2024-12-04 | C5: 4368
A6: 5 | B6: 2025-01-04 | C6: 4368
A7: 6 | B7: 2025-02-04 | C7: 4368
A8: 7 | B8: 2025-03-04 | C8: 4368
A9: 8 | B9: 2025-04-04 | C9: 4368
A10: 9 | B10: 2025-05-04 | C10: 4368
A11: 10 | B11: 2025-06-04 | C11: 4368
A12: 11 | B12: 2025-07-04 | C12: 4368
A13: 12 | B13: 2025-08-04 | C13: 4368
A14: 13 | B14: 2025-09-04 | C14: 4368
... A21: 20 | B21: 2026-04-04 | C21: 3276

Sheet Overall
A1: Label | B1: Amount | C1: Note 1 | D1: Note 2
A2: Fixed Deposit | B2: 4901776.3
A3: Bank | B3: 358157.92
A4: Mutal_fund | B4: 847649.25
A5: Stocks | B5: 649247.33
A6: Capital | B6: 3018376.1
A7: Chits | B7: 842475
B8: =SUM(Table12[Amount]) -> 10617682
H10: =B2+B3+B7+SUM(Loans!C2:C6)+2100000+8000000 -> 18134777

Sheet Sheet1
A1: corporate
A2: salary | B2: 2986000
A3: variable | B3: 500000
A4: cto bonus | B4: =C4*90.2 -> 90200 | C4: 1000
A5: pf | B5: 107416
A6: pfintrest | B6: =8.25*C6/100 -> 74111.895 | C6: =Loans!C8 -> 898326
A7: graduty | B7: =C7/5 -> 51680.8 | C7: =Table9[[#This Row],[Amount]] -> 258404
E8: =SUM(B2:B7) -> 3809408.7
A9: personal
A10: srinivas mama | B10: =C10*12 -> 150000 | C10: 12500
A11: fd intrest | B11: =C11*6.8/100 -> 321928.33 | C11: ='Fixed Deposit'!C42 -> 4734240.2
A12: mutual funds | B12: =C12*0.08 -> 67717.232 | C12: ='Mutal Funds'!L13 -> 846465.4
A13: stocks | B13: =C13*0.1 -> 65532.675 | C13: =Stocks!J25 -> 655326.75
A14: chits | B14: =C14/2 -> 125000 | C14: =250000 -> 250000
A15: prasad | B15: =C15*11 -> 495000 | C15: 45000
E16: =SUM(B10:B15) -> 1225178.2
E17: =SUM(E8,E16) -> 5034586.9 | G17: =E17*0.7/12 -> 293684.24
A18: mom
A19: pension | B19: =C19*12 -> 24192 | C19: 2016
A20: ramesh | B20: =C20*12 -> 120000 | C20: 10000
A21: venkatest | B21: =12*C21 -> 156000 | C21: 13000
A23: mani
B24: 1600000
A26: Home | B26: =C26+[1]Loans!C6 -> 5908283.1 | C26: 6500000 | E26: =B26*0.05 -> 295414.16
B31: =SUM(B1:B24) -> 6934778.9
